frontend/__init__.py
frontend/apps/__init__.py
frontend/apps/dashboard.py
frontend/apps/external_links.py
core_frontend-0.1.dist-info/METADATA
core_frontend-0.1.dist-info/WHEEL
core_frontend-0.1.dist-info/top_level.txt
core_frontend-0.1.dist-info/RECORD
