Metadata-Version: 2.1
Name: core-frontend
Version: 0.1
Summary: Research CORE ERM - frontend module
Home-page: https://github.com/research-core/core-frontend
Author: Ricardo Ribeiro, Hugo Cachitas
Author-email: ricardojvr@gmail.com, hugo.cachitas@research.fchampalimaud.org
License: MIT
Platform: UNKNOWN
